x_access_dumper/__init__.py
x_access_dumper/__main__.py
x_access_dumper/cli.py
x_access_dumper/dumper.py
x_access_dumper/errors.py
x_access_dumper/logger.py
x_access_dumper/utils.py
x_access_dumper/wrappers.py
x_access_dumper-0.2.1.dist-info/entry_points.txt
x_access_dumper-0.2.1.dist-info/WHEEL
x_access_dumper-0.2.1.dist-info/METADATA
x_access_dumper-0.2.1.dist-info/RECORD
